yroom-0.0.10.dist-info/METADATA
yroom-0.0.10.dist-info/WHEEL
yroom-0.0.10.dist-info/license_files/LICENSE
yroom/__init__.py
yroom/__init__.pyi
yroom/py.typed
yroom/yroom.cpython-311-darwin.so
yroom-0.0.10.dist-info/RECORD
