Metadata-Version: 2.1
Name: yroom
Version: 0.0.10
Classifier: Programming Language :: Rust
Classifier: Programming Language :: Python :: Implementation :: CPython
Classifier: Programming Language :: Python :: Implementation :: PyPy
Requires-Dist: pytest; extra == 'test'
Requires-Dist: ypy; extra == 'test'
Requires-Dist: black; extra == 'test'
Requires-Dist: ruff; extra == 'test'
Provides-Extra: test
License-File: LICENSE
Summary: Yjs sync and awareness protocol handler for a non-editing client (e.g. server)
Author-email: Stefan Wehrmeyer <mail@stefanwehrmeyer.com>
Requires-Python: >=3.7
Project-URL: Homepage, https://github.com/stefanw/yroom
